Pluto-1.1.1.data/purelib/Pluto/Pluto.py
Pluto-1.1.1.data/purelib/Pluto/PlutoLib.dll
Pluto-1.1.1.data/purelib/Pluto/PlutoLib.lib
Pluto-1.1.1.data/purelib/Pluto/_Pluto.pyd
Pluto-1.1.1.data/purelib/Pluto/__init__.py
Pluto-1.1.1.data/purelib/Pluto/install.py
Pluto-1.1.1.data/purelib/Pluto/pluto.exe
Pluto-1.1.1.data/purelib/Pluto/Libraries/GLM.py
Pluto-1.1.1.data/purelib/Pluto/Libraries/Libraries.py
Pluto-1.1.1.data/purelib/Pluto/Libraries/_GLM.pyd
Pluto-1.1.1.data/purelib/Pluto/Libraries/_Libraries.pyd
Pluto-1.1.1.data/purelib/Pluto/Libraries/__init__.py
Pluto-1.1.1.data/purelib/Pluto/Resources/Defaults/CubeFrame.obj
Pluto-1.1.1.data/purelib/Pluto/Resources/Defaults/brdf-lut.ktx
Pluto-1.1.1.data/purelib/Pluto/Resources/Defaults/checker.ktx
Pluto-1.1.1.data/purelib/Pluto/Resources/Defaults/default.png
Pluto-1.1.1.data/purelib/Pluto/Resources/Defaults/defaultVolume.raw
Pluto-1.1.1.data/purelib/Pluto/Resources/Defaults/missing-model.obj
Pluto-1.1.1.data/purelib/Pluto/Resources/Defaults/missing-texcube.ktx
Pluto-1.1.1.data/purelib/Pluto/Resources/Defaults/missing-texture.ktx
Pluto-1.1.1.data/purelib/Pluto/Resources/Defaults/missing-texture.png
Pluto-1.1.1.data/purelib/Pluto/Resources/Defaults/missing-volume.ktx
Pluto-1.1.1.data/purelib/Pluto/Resources/Defaults/VRModels/valve_controller_knu_ev2_0_left/body.mtl
Pluto-1.1.1.data/purelib/Pluto/Resources/Defaults/VRModels/valve_controller_knu_ev2_0_left/body.obj
Pluto-1.1.1.data/purelib/Pluto/Resources/Defaults/VRModels/valve_controller_knu_ev2_0_left/button_a.mtl
Pluto-1.1.1.data/purelib/Pluto/Resources/Defaults/VRModels/valve_controller_knu_ev2_0_left/button_a.obj
Pluto-1.1.1.data/purelib/Pluto/Resources/Defaults/VRModels/valve_controller_knu_ev2_0_left/button_b.mtl
Pluto-1.1.1.data/purelib/Pluto/Resources/Defaults/VRModels/valve_controller_knu_ev2_0_left/button_b.obj
Pluto-1.1.1.data/purelib/Pluto/Resources/Defaults/VRModels/valve_controller_knu_ev2_0_left/button_system.mtl
Pluto-1.1.1.dist-info/METADATA
Pluto-1.1.1.dist-info/WHEEL
Pluto-1.1.1.dist-info/top_level.txt
Pluto-1.1.1.dist-info/RECORD
