Metadata-Version: 2.1
Name: Pluto
Version: 1.1.1
Summary: Interactive IPython kernel for Jupyter with a built in Vulkan graphics engine
Home-page: https://github.com/n8vm/Pluto
Author: Nathan Morrical
Author-email: natemorrical@gmail.com
License: UNKNOWN
Platform: UNKNOWN
Classifier: Intended Audience :: Developers
Classifier: License :: OSI Approved :: MIT License
Classifier: Programming Language :: Python :: 3.7
Requires-Python: >3.5.2
